dictstruct/__init__.py
dictstruct/_lazy.py
dictstruct/_main.py
dictstruct/py.typed
dictstruct-0.0.9.dist-info/METADATA
dictstruct-0.0.9.dist-info/WHEEL
dictstruct-0.0.9.dist-info/licenses/LICENSE
dictstruct-0.0.9.dist-info/RECORD
